juice/__init__.py
juice/cli.py
juice_gpu-0.1.0.dist-info/METADATA
juice_gpu-0.1.0.dist-info/WHEEL
juice_gpu-0.1.0.dist-info/top_level.txt
juice_gpu-0.1.0.dist-info/RECORD
